{
	"code": 200,
	"message": "Success",
	"userGames": [
		{
			"userNum": 3206374,
			"nickname": "킹갓",
			"gameId": 27619566,
			"seasonId": 0,
			"matchingMode": 6,
			"matchingTeamMode": 4,
			"characterNum": 46,
			"skinCode": 1046002,
			"characterLevel": 19,
			"gameRank": 2,
			"playerKill": 9,
			"playerAssistant": 8,
			"monsterKill": 11,
			"bestWeapon": 16,
			"bestWeaponLevel": 19,
			"masteryLevel": {
				"16": 19,
				"201": 20,
				"202": 6,
				"101": 6,
				"102": 6,
				"103": 6
			},
			"equipment": {
				"0": 102501,
				"1": 202418,
				"2": 201418,
				"3": 203508,
				"4": 204414
			},
			"versionMajor": 3,
			"versionMinor": 0,
			"language": "Korean",
			"skillLevelInfo": {
				"1046500": 3,
				"1046400": 5,
				"1046300": 4,
				"1046200": 5,
				"1046100": 2,
				"3016000": 2
			},
			"skillOrderInfo": {
				"1": 1046500,
				"2": 1046400,
				"3": 1046300,
				"4": 1046200,
				"5": 1046100,
				"6": 1046100,
				"7": 1046200,
				"8": 1046200,
				"9": 1046200,
				"10": 1046200,
				"11": 1046500,
				"12": 3016000,
				"13": 1046400,
				"14": 1046400,
				"15": 1046400,
				"16": 1046400,
				"17": 3016000,
				"18": 1046500,
				"19": 1046300,
				"20": 1046300,
				"21": 1046300
			},
			"serverName": "Seoul",
			"maxHp": 2495,
			"maxSp": 977,
			"attackPower": 355,
			"defense": 125,
			"hpRegen": 4.37,
			"spRegen": 4.86,
			"attackSpeed": 1.41,
			"moveSpeed": 4.05,
			"outOfCombatMoveSpeed": 4.05,
			"sightRange": 10.0,
			"attackRange": 2.08,
			"criticalStrikeChance": 27.0,
			"criticalStrikeDamage": 24.0,
			"coolDownReduction": 0.0,
			"lifeSteal": 0.0,
			"normalLifeSteal": 0.16,
			"skillLifeSteal": 0.0,
			"amplifierToMonster": 12.0,
			"trapDamage": 0.0,
			"bonusCoin": 0,
			"gainExp": 79,
			"baseExp": 79,
			"bonusExp": 0,
			"startDtm": "2023-09-08T23:07:33.033+0900",
			"duration": 746,
			"playTime": 741,
			"watchTime": 0,
			"totalTime": 741,
			"survivableTime": 25,
			"botAdded": 0,
			"botRemain": 0,
			"restrictedAreaAccelerated": 0,
			"safeAreas": 0,
			"teamNumber": 2,
			"preMade": 1,
			"eventMissionResult": {},
			"gainedNormalMmrKFactor": 20.0,
			"victory": 0,
			"craftUncommon": 0,
			"craftRare": 0,
			"craftEpic": 0,
			"craftLegend": 0,
			"damageToPlayer": 32073,
			"damageToPlayer_trap": 0,
			"damageToPlayer_basic": 18495,
			"damageToPlayer_skill": 6910,
			"damageToPlayer_itemSkill": 0,
			"damageToPlayer_direct": 6668,
			"damageToPlayer_uniqueSkill": 0,
			"damageFromPlayer": 29072,
			"damageFromPlayer_trap": 0,
			"damageFromPlayer_basic": 1684,
			"damageFromPlayer_skill": 24161,
			"damageFromPlayer_itemSkill": 1549,
			"damageFromPlayer_direct": 1678,
			"damageFromPlayer_uniqueSkill": 0,
			"damageToMonster": 16095,
			"damageToMonster_trap": 0,
			"damageToMonster_basic": 14635,
			"damageToMonster_skill": 723,
			"damageToMonster_itemSkill": 0,
			"damageToMonster_direct": 737,
			"damageToMonster_uniqueSkill": 0,
			"damageFromMonster": 920,
			"killMonsters": {
				"4": 1,
				"3": 2,
				"5": 4,
				"11": 2,
				"6": 2
			},
			"healAmount": 16513,
			"teamRecover": 889,
			"protectAbsorb": 5643,
			"addSurveillanceCamera": 0,
			"addTelephotoCamera": 0,
			"removeSurveillanceCamera": 0,
			"removeTelephotoCamera": 0,
			"useHyperLoop": 12,
			"useSecurityConsole": 0,
			"giveUp": 0,
			"teamSpectator": 0,
			"routeIdOfStart": 0,
			"routeSlotId": 0,
			"placeOfStart": "160",
			"matchSize": 8,
			"teamKill": 21,
			"totalFieldKill": 21,
			"accountLevel": 179,
			"killerUserNum": 1736707,
			"killer": "player",
			"killDetail": "샌토바보아니다",
			"causeOfDeath": "윌슨! 도와줘",
			"placeOfDeath": "2030",
			"killerCharacter": "Sissela",
			"killerWeapon": "DirectFire",
			"killerUserNum2": 2212773,
			"killer2": "player",
			"killDetail2": "폴더바보아니다",
			"causeOfDeath2": "날카로운 꽃 - 강화2",
			"placeOfDeath2": "2030",
			"killerCharacter2": "Laura",
			"killerWeapon2": "Whip",
			"killerUserNum3": 2212773,
			"killer3": "player",
			"killDetail3": "폴더바보아니다",
			"causeOfDeath3": "날카로운 꽃 - 강화1",
			"placeOfDeath3": "2030",
			"killerCharacter3": "Laura",
			"killerWeapon3": "Whip",
			"fishingCount": 0,
			"useEmoticonCount": 16,
			"expireDtm": "2023-12-07T23:20:00.000+0900",
			"traitFirstCore": 7000401,
			"traitFirstSub": [],
			"traitSecondSub": [
				7922903,
				7920101,
				7900101
			],
			"airSupplyOpenCount": [
				0,
				0,
				0,
				0,
				0,
				0,
				0
			],
			"foodCraftCount": [
				0,
				0,
				0,
				0,
				0,
				0,
				0
			],
			"beverageCraftCount": [
				0,
				0,
				0,
				0,
				0,
				0,
				0
			],
			"rankPoint": 0,
			"totalTurbineTakeOver": 5,
			"startingItems": [
				102405,
				202412,
				201418,
				203405,
				204403
			],
			"usedNormalHealPack": 8,
			"usedReinforcedHealPack": 1,
			"usedNormalShieldPack": 6,
			"usedReinforceShieldPack": 2,
			"totalVFCredits": [
				62,
				59,
				35,
				39,
				38,
				34,
				56,
				112,
				39,
				23,
				39,
				17,
				18,
				0,
				0,
				0,
				0,
				0,
				0,
				0
			],
			"usedVFCredits": [
				60,
				0,
				0,
				110,
				30,
				0,
				0,
				220,
				9,
				50,
				0,
				3,
				80,
				0,
				0,
				0,
				0,
				0,
				0,
				0
			],
			"sumTotalVFCredits": 571,
			"sumUsedVFCredits": 562,
			"finalInfusion": [
				81,
				28,
				1
			],
			"craftMythic": 0,
			"playerDeaths": 6,
			"killGamma": false,
			"scoredPoint": [
				0,
				1,
				1,
				0,
				1,
				2,
				1,
				0,
				1,
				0,
				3,
				0,
				0,
				0,
				0,
				0,
				0,
				0,
				0,
				0
			],
			"killDetails": "{\"15\":5,\"47\":3,\"58\":1}",
			"deathDetails": "{\"15\":2,\"47\":4}",
			"killsPhaseOne": 2,
			"killsPhaseTwo": 2,
			"killsPhaseThree": 5,
			"deathsPhaseOne": 1,
			"deathsPhaseTwo": 1,
			"deathsPhaseThree": 4,
			"usedPairLoop": 12,
			"ccTimeToPlayer": 19.7,
			"creditSource": {
				"PhaseStart": 25.0,
				"StartItem": 15.0,
				"ItemShredder": 106.0,
				"InfusionStore": 360.0,
				"KillMutantWildDog": 10.0,
				"KillMutantBoar": 24.0,
				"TimeElapsed": 182.0,
				"KillMutantWolf": 24.0,
				"KillPlayerMerge": 85.0,
				"KillAssist": 32.0,
				"KillMutantBear": 62.0,
				"Infusion": 90.0,
				"KillDrone": 6.0,
				"InfusionRelic": 100.0,
				"InfusionReroll": 12.0
			},
			"boughtInfusion": "{\"10001\":12,\"81\":1,\"2001\":1,\"28\":1,\"1\":1}",
			"itemTransferredConsole": [],
			"itemTransferredDrone": [],
			"afk": false,
			"escapeState": 0,
			"totalDoubleKill": 0,
			"totalTripleKill": 0,
			"totalQuadraKill": 0,
			"totalExtraKill": 0,
			"collectItemForLog": [
				0,
				0,
				0,
				0,
				0,
				0,
				0
			],
			"equipFirstItemForLog": {
				"0": [
					102405
				],
				"1": [
					202412
				],
				"2": [
					201418
				],
				"3": [
					203405
				],
				"4": [
					204403
				]
			},
			"battleZone1AreaCode": 0,
			"battleZone1BattleMark": 0,
			"battleZone1ItemCode": [],
			"battleZone2AreaCode": 0,
			"battleZone2BattleMark": 0,
			"battleZone2ItemCode": [],
			"battleZone3AreaCode": 0,
			"battleZone3BattleMark": 0,
			"battleZone3ItemCode": [],
			"battleZonePlayerKill": 0,
			"battleZoneDeaths": 0,
			"battleZone1Winner": 0,
			"battleZone2Winner": 0,
			"battleZone3Winner": 0,
			"battleZone1BattleMarkCount": 0,
			"battleZone2BattleMarkCount": 0,
			"battleZone3BattleMarkCount": 0,
			"tacticalSkillGroup": 500030,
			"tacticalSkillLevel": 1,
			"totalGainVFCredit": 571,
			"killPlayerGainVFCredit": 85,
			"killChickenGainVFCredit": 0,
			"killBoarGainVFCredit": 24,
			"killWildDogGainVFCredit": 10,
			"killWolfGainVFCredit": 24,
			"killBearGainVFCredit": 62,
			"killOmegaGainVFCredit": 0,
			"killBatGainVFCredit": 0,
			"killWicklineGainVFCredit": 0,
			"killAlphaGainVFCredit": 0,
			"killItemBountyGainVFCredit": 0,
			"killDroneGainVFCredit": 6,
			"killGammaGainVFCredit": 0,
			"killTurretGainVFCredit": 0,
			"itemShredderGainVFCredit": 106,
			"totalUseVFCredit": 562,
			"remoteDroneUseVFCreditMySelf": 0,
			"remoteDroneUseVFCreditAlly": 0,
			"transferConsoleFromMaterialUseVFCredit": 0,
			"transferConsoleFromEscapeKeyUseVFCredit": 0,
			"transferConsoleFromRevivalUseVFCredit": 0,
			"tacticalSkillUpgradeUseVFCredit": 0,
			"infusionReRollUseVFCredit": 12,
			"infusionTraitUseVFCredit": 90,
			"infusionRelicUseVFCredit": 100,
			"infusionStoreUseVFCredit": 360,
			"teamElimination": 0,
			"teamDown": 21,
			"teamBattleZoneDown": 0,
			"teamRepeatDown": 0,
			"adaptiveForce": 0,
			"adaptiveForceAttack": 0,
			"adaptiveForceAmplify": 0,
			"skillAmp": 0,
			"campFireCraftUncommon": 0,
			"campFireCraftRare": 0,
			"campFireCraftEpic": 0,
			"campFireCraftLegendary": 0,
			"cobaltRandomPickRemoveCharacter": 14,
			"tacticalSkillUseCount": 9,
			"creditRevivalCount": 0,
			"creditRevivedOthersCount": 0,
			"timeSpentInBriefingRoom": 0,
			"IsLeavingBeforeCreditRevivalTerminate": false,
			"crGetAnimal": 6,
			"crGetMutant": 120,
			"crGetPhaseStart": 25,
			"crGetKill": 85,
			"crGetAssist": 32,
			"crGetTimeElapsed": 182,
			"crGetCreditBonus": 0,
			"crUseRemoteDrone": 0,
			"crUseUpgradeTacticalSkill": 0,
			"crUseTreeOfLife": 0,
			"crUseMeteorite": 0,
			"crUseMythril": 0,
			"crUseForceCore": 0,
			"crUseVFBloodSample": 0,
			"crUseActivationModule": 0,
			"crUseRootkit": 0,
			"mmrGainInGame": 0,
			"isLeavingBeforeCreditRevivalTerminate": false
		},
		{
			"userNum": 2582943,
			"nickname": "티잔",
			"gameId": 27619566,
			"seasonId": 0,
			"matchingMode": 6,
			"matchingTeamMode": 4,
			"characterNum": 58,
			"skinCode": 1058002,
			"characterLevel": 19,
			"gameRank": 1,
			"playerKill": 3,
			"playerAssistant": 12,
			"monsterKill": 31,
			"bestWeapon": 10,
			"bestWeaponLevel": 17,
			"masteryLevel": {
				"10": 17,
				"201": 17,
				"202": 6,
				"101": 6,
				"102": 6,
				"103": 6
			},
			"equipment": {
				"0": 117502,
				"1": 202501,
				"2": 201503,
				"3": 203510,
				"4": 204413
			},
			"versionMajor": 3,
			"versionMinor": 0,
			"language": "Korean",
			"skillLevelInfo": {
				"1058500": 2,
				"1058100": 2,
				"1058400": 5,
				"1058300": 4,
				"1058200": 5,
				"3010000": 2,
				"1058510": 1
			},
			"skillOrderInfo": {
				"1": 1058500,
				"2": 1058100,
				"3": 1058100,
				"4": 1058400,
				"5": 1058300,
				"6": 1058200,
				"7": 1058200,
				"8": 1058200,
				"9": 1058200,
				"10": 1058200,
				"11": 1058500,
				"12": 3010000,
				"13": 1058400,
				"14": 1058400,
				"15": 1058400,
				"16": 1058400,
				"17": 1058510,
				"18": 1058300,
				"19": 3010000,
				"20": 1058300,
				"21": 1058300
			},
			"serverName": "Seoul",
			"maxHp": 2266,
			"maxSp": 1479,
			"attackPower": 189,
			"defense": 145,
			"hpRegen": 4.16,
			"spRegen": 8.45,
			"attackSpeed": 1.25,
			"moveSpeed": 4.13,
			"outOfCombatMoveSpeed": 4.13,
			"sightRange": 10.0,
			"attackRange": 5.4,
			"criticalStrikeChance": 0.0,
			"criticalStrikeDamage": 0.0,
			"coolDownReduction": 32.0,
			"lifeSteal": 0.0,
			"normalLifeSteal": 0.0,
			"skillLifeSteal": 0.0,
			"amplifierToMonster": 12.0,
			"trapDamage": 0.0,
			"bonusCoin": 0,
			"gainExp": 119,
			"baseExp": 119,
			"bonusExp": 0,
			"startDtm": "2023-09-08T23:07:33.033+0900",
			"duration": 746,
			"playTime": 741,
			"watchTime": 0,
			"totalTime": 741,
			"survivableTime": 25,
			"botAdded": 0,
			"botRemain": 0,
			"restrictedAreaAccelerated": 0,
			"safeAreas": 0,
			"teamNumber": 1,
			"preMade": 2,
			"eventMissionResult": {},
			"gainedNormalMmrKFactor": 20.0,
			"victory": 1,
			"craftUncommon": 0,
			"craftRare": 0,
			"craftEpic": 0,
			"craftLegend": 0,
			"damageToPlayer": 19924,
			"damageToPlayer_trap": 0,
			"damageToPlayer_basic": 2665,
			"damageToPlayer_skill": 16614,
			"damageToPlayer_itemSkill": 91,
			"damageToPlayer_direct": 554,
			"damageToPlayer_uniqueSkill": 0,
			"damageFromPlayer": 22380,
			"damageFromPlayer_trap": 0,
			"damageFromPlayer_basic": 7433,
			"damageFromPlayer_skill": 10127,
			"damageFromPlayer_itemSkill": 524,
			"damageFromPlayer_direct": 4296,
			"damageFromPlayer_uniqueSkill": 0,
			"damageToMonster": 16893,
			"damageToMonster_trap": 0,
			"damageToMonster_basic": 2297,
			"damageToMonster_skill": 14445,
			"damageToMonster_itemSkill": 151,
			"damageToMonster_direct": 0,
			"damageToMonster_uniqueSkill": 0,
			"damageFromMonster": 1899,
			"killMonsters": {
				"11": 25,
				"5": 4,
				"3": 1,
				"4": 1
			},
			"healAmount": 15471,
			"teamRecover": 4218,
			"protectAbsorb": 2383,
			"addSurveillanceCamera": 0,
			"addTelephotoCamera": 1,
			"removeSurveillanceCamera": 0,
			"removeTelephotoCamera": 0,
			"useHyperLoop": 6,
			"useSecurityConsole": 0,
			"giveUp": 0,
			"teamSpectator": 0,
			"routeIdOfStart": 0,
			"routeSlotId": 0,
			"placeOfStart": "2070",
			"matchSize": 8,
			"teamKill": 27,
			"totalFieldKill": 27,
			"accountLevel": 267,
			"killerUserNum": 0,
			"killer": "wildAnimal",
			"killDetail": "Turret",
			"causeOfDeath": "basicAttack",
			"placeOfDeath": "2040",
			"killerCharacter": "Turret",
			"killerWeapon": "",
			"killerUserNum2": 377032,
			"killer2": "player",
			"killDetail2": "우라라",
			"causeOfDeath2": "정밀 폭격",
			"placeOfDeath2": "2030",
			"killerCharacter2": "Alex",
			"killerWeapon2": "Tonfa",
			"killerUserNum3": 3206374,
			"killer3": "player",
			"killDetail3": "킹갓",
			"causeOfDeath3": "basicAttack",
			"placeOfDeath3": "2020",
			"killerCharacter3": "Aiden",
			"killerWeapon3": "TwoHandSword",
			"fishingCount": 0,
			"useEmoticonCount": 8,
			"expireDtm": "2023-12-07T23:19:59.059+0900",
			"traitFirstCore": 7000501,
			"traitFirstSub": [],
			"traitSecondSub": [
				7920301,
				7921501
			],
			"airSupplyOpenCount": [
				0,
				0,
				0,
				0,
				0,
				0,
				0
			],
			"foodCraftCount": [
				0,
				0,
				0,
				0,
				0,
				0,
				0
			],
			"beverageCraftCount": [
				0,
				0,
				0,
				0,
				0,
				0,
				0
			],
			"rankPoint": 0,
			"totalTurbineTakeOver": 2,
			"startingItems": [
				117501,
				202406,
				201412,
				203403,
				204415
			],
			"usedNormalHealPack": 10,
			"usedReinforcedHealPack": 0,
			"usedNormalShieldPack": 3,
			"usedReinforceShieldPack": 0,
			"totalVFCredits": [
				57,
				58,
				50,
				41,
				66,
				68,
				123,
				37,
				39,
				85,
				27,
				70,
				11,
				0,
				0,
				0,
				0,
				0,
				0,
				0
			],
			"usedVFCredits": [
				30,
				30,
				0,
				0,
				0,
				30,
				340,
				0,
				100,
				30,
				0,
				120,
				0,
				0,
				0,
				0,
				0,
				0,
				0,
				0
			],
			"sumTotalVFCredits": 732,
			"sumUsedVFCredits": 680,
			"finalInfusion": [
				34,
				62,
				0
			],
			"craftMythic": 0,
			"playerDeaths": 3,
			"killGamma": false,
			"scoredPoint": [
				0,
				0,
				0,
				1,
				1,
				0,
				0,
				1,
				2,
				1,
				0,
				0,
				0,
				0,
				0,
				0,
				0,
				0,
				0,
				0
			],
			"killDetails": "{\"65\":2,\"2\":1}",
			"deathDetails": "{\"27\":1,\"46\":1}",
			"killsPhaseOne": 0,
			"killsPhaseTwo": 1,
			"killsPhaseThree": 2,
			"deathsPhaseOne": 0,
			"deathsPhaseTwo": 1,
			"deathsPhaseThree": 2,
			"usedPairLoop": 6,
			"ccTimeToPlayer": 13.250001,
			"creditSource": {
				"PhaseStart": 25.0,
				"StartItem": 20.0,
				"InfusionStore": 540.0,
				"ItemShredder": 188.0,
				"KillMutantWildDog": 22.0,
				"KillMutantWolf": 36.0,
				"TimeElapsed": 180.0,
				"KillMutantBoar": 28.0,
				"KillDrone": 75.0,
				"KillPlayerMerge": 68.0,
				"KillAssist": 48.0,
				"KillMutantBear": 12.0,
				"KillOmega": 30.0,
				"InfusionRelic": 100.0,
				"Infusion": 40.0
			},
			"boughtInfusion": "{\"10001\":18,\"2004\":1,\"34\":1,\"62\":1}",
			"itemTransferredConsole": [],
			"itemTransferredDrone": [],
			"afk": false,
			"escapeState": 0,
			"totalDoubleKill": 0,
			"totalTripleKill": 0,
			"totalQuadraKill": 0,
			"totalExtraKill": 0,
			"collectItemForLog": [
				0,
				0,
				0,
				0,
				0,
				0,
				0
			],
			"equipFirstItemForLog": {
				"0": [
					117501
				],
				"1": [
					202406
				],
				"2": [
					201412
				],
				"3": [
					203403
				],
				"4": [
					204415
				]
			},
			"battleZone1AreaCode": 0,
			"battleZone1BattleMark": 0,
			"battleZone1ItemCode": [],
			"battleZone2AreaCode": 0,
			"battleZone2BattleMark": 0,
			"battleZone2ItemCode": [],
			"battleZone3AreaCode": 0,
			"battleZone3BattleMark": 0,
			"battleZone3ItemCode": [],
			"battleZonePlayerKill": 0,
			"battleZoneDeaths": 0,
			"battleZone1Winner": 0,
			"battleZone2Winner": 0,
			"battleZone3Winner": 0,
			"battleZone1BattleMarkCount": 0,
			"battleZone2BattleMarkCount": 0,
			"battleZone3BattleMarkCount": 0,
			"tacticalSkillGroup": 500060,
			"tacticalSkillLevel": 1,
			"totalGainVFCredit": 732,
			"killPlayerGainVFCredit": 68,
			"killChickenGainVFCredit": 0,
			"killBoarGainVFCredit": 28,
			"killWildDogGainVFCredit": 22,
			"killWolfGainVFCredit": 36,
			"killBearGainVFCredit": 12,
			"killOmegaGainVFCredit": 30,
			"killBatGainVFCredit": 0,
			"killWicklineGainVFCredit": 0,
			"killAlphaGainVFCredit": 0,
			"killItemBountyGainVFCredit": 0,
			"killDroneGainVFCredit": 75,
			"killGammaGainVFCredit": 0,
			"killTurretGainVFCredit": 0,
			"itemShredderGainVFCredit": 188,
			"totalUseVFCredit": 680,
			"remoteDroneUseVFCreditMySelf": 0,
			"remoteDroneUseVFCreditAlly": 0,
			"transferConsoleFromMaterialUseVFCredit": 0,
			"transferConsoleFromEscapeKeyUseVFCredit": 0,
			"transferConsoleFromRevivalUseVFCredit": 0,
			"tacticalSkillUpgradeUseVFCredit": 0,
			"infusionReRollUseVFCredit": 0,
			"infusionTraitUseVFCredit": 40,
			"infusionRelicUseVFCredit": 100,
			"infusionStoreUseVFCredit": 540,
			"teamElimination": 0,
			"teamDown": 27,
			"teamBattleZoneDown": 0,
			"teamRepeatDown": 0,
			"adaptiveForce": 0,
			"adaptiveForceAttack": 0,
			"adaptiveForceAmplify": 0,
			"skillAmp": 782,
			"campFireCraftUncommon": 0,
			"campFireCraftRare": 0,
			"campFireCraftEpic": 0,
			"campFireCraftLegendary": 0,
			"cobaltRandomPickRemoveCharacter": 4,
			"tacticalSkillUseCount": 10,
			"creditRevivalCount": 0,
			"creditRevivedOthersCount": 0,
			"timeSpentInBriefingRoom": 0,
			"IsLeavingBeforeCreditRevivalTerminate": false,
			"crGetAnimal": 105,
			"crGetMutant": 98,
			"crGetPhaseStart": 25,
			"crGetKill": 68,
			"crGetAssist": 48,
			"crGetTimeElapsed": 180,
			"crGetCreditBonus": 0,
			"crUseRemoteDrone": 0,
			"crUseUpgradeTacticalSkill": 0,
			"crUseTreeOfLife": 0,
			"crUseMeteorite": 0,
			"crUseMythril": 0,
			"crUseForceCore": 0,
			"crUseVFBloodSample": 0,
			"crUseActivationModule": 0,
			"crUseRootkit": 0,
			"mmrGainInGame": 0,
			"isLeavingBeforeCreditRevivalTerminate": false
		},
		{
			"userNum": 2212773,
			"nickname": "폴더바보아니다",
			"gameId": 27619566,
			"seasonId": 0,
			"matchingMode": 6,
			"matchingTeamMode": 4,
			"characterNum": 47,
			"skinCode": 1047002,
			"characterLevel": 20,
			"gameRank": 1,
			"playerKill": 11,
			"playerAssistant": 14,
			"monsterKill": 16,
			"bestWeapon": 4,
			"bestWeaponLevel": 19,
			"masteryLevel": {
				"4": 19,
				"201": 20,
				"202": 6,
				"101": 6,
				"102": 6,
				"103": 6
			},
			"equipment": {
				"0": 109501,
				"1": 202503,
				"2": 201411,
				"3": 203502,
				"4": 204402
			},
			"versionMajor": 3,
			"versionMinor": 0,
			"language": "Korean",
			"skillLevelInfo": {
				"1047100": 2,
				"1047500": 3,
				"1047400": 5,
				"1047300": 4,
				"1047200": 5,
				"3004000": 2
			},
			"skillOrderInfo": {
				"1": 1047100,
				"2": 1047100,
				"3": 1047500,
				"4": 1047400,
				"5": 1047300,
				"6": 1047200,
				"7": 1047200,
				"8": 1047200,
				"9": 1047200,
				"10": 1047200,
				"11": 3004000,
				"12": 1047500,
				"13": 1047400,
				"14": 1047400,
				"15": 1047400,
				"16": 1047400,
				"17": 3004000,
				"18": 1047500,
				"19": 1047300,
				"20": 1047300,
				"21": 1047300
			},
			"serverName": "Seoul",
			"maxHp": 2772,
			"maxSp": 1202,
			"attackPower": 169,
			"defense": 146,
			"hpRegen": 5.68,
			"spRegen": 6.86,
			"attackSpeed": 1.54,
			"moveSpeed": 3.95,
			"outOfCombatMoveSpeed": 3.95,
			"sightRange": 10.0,
			"attackRange": 2.8,
			"criticalStrikeChance": 70.0,
			"criticalStrikeDamage": -1.0,
			"coolDownReduction": 12.0,
			"lifeSteal": 0.22,
			"normalLifeSteal": 0.0,
			"skillLifeSteal": 0.0,
			"amplifierToMonster": 12.0,
			"trapDamage": 0.0,
			"bonusCoin": 0,
			"gainExp": 120,
			"baseExp": 120,
			"bonusExp": 0,
			"startDtm": "2023-09-08T23:07:33.033+0900",
			"duration": 746,
			"playTime": 741,
			"watchTime": 0,
			"totalTime": 741,
			"survivableTime": 25,
			"botAdded": 0,
			"botRemain": 0,
			"restrictedAreaAccelerated": 0,
			"safeAreas": 0,
			"teamNumber": 1,
			"preMade": 2,
			"eventMissionResult": {},
			"gainedNormalMmrKFactor": 20.0,
			"victory": 1,
			"craftUncommon": 0,
			"craftRare": 0,
			"craftEpic": 0,
			"craftLegend": 0,
			"damageToPlayer": 29476,
			"damageToPlayer_trap": 0,
			"damageToPlayer_basic": 1534,
			"damageToPlayer_skill": 24073,
			"damageToPlayer_itemSkill": 0,
			"damageToPlayer_direct": 3869,
			"damageToPlayer_uniqueSkill": 0,
			"damageFromPlayer": 32623,
			"damageFromPlayer_trap": 0,
			"damageFromPlayer_basic": 11734,
			"damageFromPlayer_skill": 14487,
			"damageFromPlayer_itemSkill": 771,
			"damageFromPlayer_direct": 5631,
			"damageFromPlayer_uniqueSkill": 0,
			"damageToMonster": 15986,
			"damageToMonster_trap": 0,
			"damageToMonster_basic": 1701,
			"damageToMonster_skill": 14285,
			"damageToMonster_itemSkill": 0,
			"damageToMonster_direct": 0,
			"damageToMonster_uniqueSkill": 0,
			"damageFromMonster": 2244,
			"killMonsters": {
				"1": 1,
				"4": 1,
				"5": 2,
				"3": 1,
				"6": 1,
				"11": 10
			},
			"healAmount": 19081,
			"teamRecover": 584,
			"protectAbsorb": 3673,
			"addSurveillanceCamera": 0,
			"addTelephotoCamera": 1,
			"removeSurveillanceCamera": 0,
			"removeTelephotoCamera": 0,
			"useHyperLoop": 10,
			"useSecurityConsole": 0,
			"giveUp": 0,
			"teamSpectator": 0,
			"routeIdOfStart": 0,
			"routeSlotId": 0,
			"placeOfStart": "160",
			"matchSize": 8,
			"teamKill": 27,
			"totalFieldKill": 27,
			"accountLevel": 181,
			"killerUserNum": 411349,
			"killer": "player",
			"killDetail": "우엉은맛있우엉",
			"causeOfDeath": "고정 사격",
			"placeOfDeath": "2030",
			"killerCharacter": "Aya",
			"killerWeapon": "SniperRifle",
			"killerUserNum2": 3206374,
			"killer2": "player",
			"killDetail2": "킹갓",
			"causeOfDeath2": "basicAttack",
			"placeOfDeath2": "2010",
			"killerCharacter2": "Aiden",
			"killerWeapon2": "TwoHandSword",
			"killerUserNum3": 3206374,
			"killer3": "player",
			"killDetail3": "킹갓",
			"causeOfDeath3": "basicAttack",
			"placeOfDeath3": "2010",
			"killerCharacter3": "Aiden",
			"killerWeapon3": "TwoHandSword",
			"fishingCount": 0,
			"useEmoticonCount": 19,
			"expireDtm": "2023-12-07T23:20:00.000+0900",
			"traitFirstCore": 7000401,
			"traitFirstSub": [],
			"traitSecondSub": [
				7920303,
				7900803,
				7923203
			],
			"airSupplyOpenCount": [
				0,
				0,
				0,
				0,
				0,
				0,
				0
			],
			"foodCraftCount": [
				0,
				0,
				0,
				0,
				0,
				0,
				0
			],
			"beverageCraftCount": [
				0,
				0,
				0,
				0,
				0,
				0,
				0
			],
			"rankPoint": 0,
			"totalTurbineTakeOver": 3,
			"startingItems": [
				109401,
				202307,
				201405,
				203403,
				204402
			],
			"usedNormalHealPack": 7,
			"usedReinforcedHealPack": 0,
			"usedNormalShieldPack": 6,
			"usedReinforceShieldPack": 1,
			"totalVFCredits": [
				30,
				53,
				33,
				60,
				74,
				88,
				77,
				49,
				31,
				52,
				43,
				65,
				8,
				0,
				0,
				0,
				0,
				0,
				0,
				0
			],
			"usedVFCredits": [
				20,
				20,
				39,
				0,
				9,
				229,
				63,
				0,
				105,
				0,
				85,
				0,
				0,
				0,
				0,
				0,
				0,
				0,
				0,
				0
			],
			"sumTotalVFCredits": 663,
			"sumUsedVFCredits": 570,
			"finalInfusion": [
				36,
				24,
				88
			],
			"craftMythic": 0,
			"playerDeaths": 6,
			"killGamma": false,
			"scoredPoint": [
				0,
				1,
				0,
				3,
				2,
				0,
				1,
				2,
				0,
				2,
				1,
				2,
				1,
				0,
				0,
				0,
				0,
				0,
				0,
				0
			],
			"killDetails": "{\"2\":4,\"46\":4,\"65\":1,\"27\":2}",
			"deathDetails": "{\"2\":2,\"46\":3,\"65\":1}",
			"killsPhaseOne": 1,
			"killsPhaseTwo": 2,
			"killsPhaseThree": 8,
			"deathsPhaseOne": 1,
			"deathsPhaseTwo": 3,
			"deathsPhaseThree": 2,
			"usedPairLoop": 10,
			"ccTimeToPlayer": 35.433334,
			"creditSource": {
				"PhaseStart": 25.0,
				"StartItem": 5.0,
				"Infusion": 200.0,
				"KillMutantWildDog": 22.0,
				"KillMutantWolf": 32.0,
				"TimeElapsed": 180.0,
				"KillMutantBoar": 28.0,
				"KillPlayerMerge": 138.0,
				"InfusionReroll": 30.0,
				"InfusionStore": 240.0,
				"KillAssist": 56.0,
				"KillMutantBear": 25.0,
				"KillOmega": 30.0,
				"InfusionRelic": 100.0,
				"ItemShredder": 92.0,
				"KillDrone": 30.0
			},
			"boughtInfusion": "{\"34\":1,\"22\":1,\"10001\":8,\"2000\":1,\"88\":1,\"35\":1,\"36\":1,\"23\":1,\"24\":1}",
			"itemTransferredConsole": [],
			"itemTransferredDrone": [],
			"afk": false,
			"escapeState": 0,
			"totalDoubleKill": 0,
			"totalTripleKill": 0,
			"totalQuadraKill": 0,
			"totalExtraKill": 0,
			"collectItemForLog": [
				0,
				0,
				0,
				0,
				0,
				0,
				0
			],
			"equipFirstItemForLog": {
				"0": [
					109401
				],
				"1": [
					202307
				],
				"2": [
					201405
				],
				"3": [
					203403
				],
				"4": [
					204402
				]
			},
			"battleZone1AreaCode": 0,
			"battleZone1BattleMark": 0,
			"battleZone1ItemCode": [],
			"battleZone2AreaCode": 0,
			"battleZone2BattleMark": 0,
			"battleZone2ItemCode": [],
			"battleZone3AreaCode": 0,
			"battleZone3BattleMark": 0,
			"battleZone3ItemCode": [],
			"battleZonePlayerKill": 0,
			"battleZoneDeaths": 0,
			"battleZone1Winner": 0,
			"battleZone2Winner": 0,
			"battleZone3Winner": 0,
			"battleZone1BattleMarkCount": 0,
			"battleZone2BattleMarkCount": 0,
			"battleZone3BattleMarkCount": 0,
			"tacticalSkillGroup": 500020,
			"tacticalSkillLevel": 1,
			"totalGainVFCredit": 663,
			"killPlayerGainVFCredit": 138,
			"killChickenGainVFCredit": 0,
			"killBoarGainVFCredit": 28,
			"killWildDogGainVFCredit": 22,
			"killWolfGainVFCredit": 32,
			"killBearGainVFCredit": 25,
			"killOmegaGainVFCredit": 30,
			"killBatGainVFCredit": 0,
			"killWicklineGainVFCredit": 0,
			"killAlphaGainVFCredit": 0,
			"killItemBountyGainVFCredit": 0,
			"killDroneGainVFCredit": 30,
			"killGammaGainVFCredit": 0,
			"killTurretGainVFCredit": 0,
			"itemShredderGainVFCredit": 92,
			"totalUseVFCredit": 570,
			"remoteDroneUseVFCreditMySelf": 0,
			"remoteDroneUseVFCreditAlly": 0,
			"transferConsoleFromMaterialUseVFCredit": 0,
			"transferConsoleFromEscapeKeyUseVFCredit": 0,
			"transferConsoleFromRevivalUseVFCredit": 0,
			"tacticalSkillUpgradeUseVFCredit": 0,
			"infusionReRollUseVFCredit": 30,
			"infusionTraitUseVFCredit": 200,
			"infusionRelicUseVFCredit": 100,
			"infusionStoreUseVFCredit": 240,
			"teamElimination": 0,
			"teamDown": 27,
			"teamBattleZoneDown": 0,
			"teamRepeatDown": 0,
			"adaptiveForce": 45,
			"adaptiveForceAttack": 39,
			"adaptiveForceAmplify": 191,
			"skillAmp": 695,
			"campFireCraftUncommon": 0,
			"campFireCraftRare": 0,
			"campFireCraftEpic": 0,
			"campFireCraftLegendary": 0,
			"cobaltRandomPickRemoveCharacter": 17,
			"tacticalSkillUseCount": 10,
			"creditRevivalCount": 0,
			"creditRevivedOthersCount": 0,
			"timeSpentInBriefingRoom": 0,
			"IsLeavingBeforeCreditRevivalTerminate": false,
			"crGetAnimal": 60,
			"crGetMutant": 107,
			"crGetPhaseStart": 25,
			"crGetKill": 138,
			"crGetAssist": 56,
			"crGetTimeElapsed": 180,
			"crGetCreditBonus": 0,
			"crUseRemoteDrone": 0,
			"crUseUpgradeTacticalSkill": 0,
			"crUseTreeOfLife": 0,
			"crUseMeteorite": 0,
			"crUseMythril": 0,
			"crUseForceCore": 0,
			"crUseVFBloodSample": 0,
			"crUseActivationModule": 0,
			"crUseRootkit": 0,
			"mmrGainInGame": 0,
			"isLeavingBeforeCreditRevivalTerminate": false
		},
		{
			"userNum": 1736707,
			"nickname": "샌토바보아니다",
			"gameId": 27619566,
			"seasonId": 0,
			"matchingMode": 6,
			"matchingTeamMode": 4,
			"characterNum": 15,
			"skinCode": 1015004,
			"characterLevel": 19,
			"gameRank": 1,
			"playerKill": 5,
			"playerAssistant": 18,
			"monsterKill": 36,
			"bestWeapon": 6,
			"bestWeaponLevel": 20,
			"masteryLevel": {
				"6": 20,
				"5": 6,
				"201": 18,
				"202": 6,
				"101": 6,
				"102": 6,
				"103": 6
			},
			"equipment": {
				"0": 113412,
				"1": 202307,
				"2": 201410,
				"3": 203403,
				"4": 204413
			},
			"versionMajor": 3,
			"versionMinor": 0,
			"language": "Korean",
			"skillLevelInfo": {
				"1015400": 5,
				"1015300": 4,
				"1015200": 5,
				"1015500": 3,
				"1015100": 2,
				"3006000": 2
			},
			"skillOrderInfo": {
				"1": 1015400,
				"2": 1015300,
				"3": 1015200,
				"4": 1015500,
				"5": 1015200,
				"6": 1015200,
				"7": 1015200,
				"8": 1015200,
				"9": 1015100,
				"10": 1015100,
				"11": 3006000,
				"12": 1015500,
				"13": 1015400,
				"14": 1015400,
				"15": 1015400,
				"16": 3006000,
				"17": 1015400,
				"18": 1015500,
				"19": 1015300,
				"20": 1015300,
				"21": 1015300
			},
			"serverName": "Seoul",
			"maxHp": 2166,
			"maxSp": 1804,
			"attackPower": 160,
			"defense": 110,
			"hpRegen": 3.82,
			"spRegen": 5.3,
			"attackSpeed": 1.15,
			"moveSpeed": 4.09,
			"outOfCombatMoveSpeed": 4.09,
			"sightRange": 10.0,
			"attackRange": 5.18,
			"criticalStrikeChance": 35.0,
			"criticalStrikeDamage": -6.0,
			"coolDownReduction": 40.0,
			"lifeSteal": 0.0,
			"normalLifeSteal": 0.0,
			"skillLifeSteal": 0.0,
			"amplifierToMonster": 12.0,
			"trapDamage": 0.0,
			"bonusCoin": 0,
			"gainExp": 119,
			"baseExp": 119,
			"bonusExp": 0,
			"startDtm": "2023-09-08T23:07:33.033+0900",
			"duration": 746,
			"playTime": 741,
			"watchTime": 0,
			"totalTime": 741,
			"survivableTime": 25,
			"botAdded": 0,
			"botRemain": 0,
			"restrictedAreaAccelerated": 0,
			"safeAreas": 0,
			"teamNumber": 1,
			"preMade": 2,
			"eventMissionResult": {},
			"gainedNormalMmrKFactor": 20.0,
			"victory": 1,
			"craftUncommon": 0,
			"craftRare": 0,
			"craftEpic": 0,
			"craftLegend": 0,
			"damageToPlayer": 32963,
			"damageToPlayer_trap": 0,
			"damageToPlayer_basic": 1613,
			"damageToPlayer_skill": 27145,
			"damageToPlayer_itemSkill": 4205,
			"damageToPlayer_direct": 0,
			"damageToPlayer_uniqueSkill": 0,
			"damageFromPlayer": 20721,
			"damageFromPlayer_trap": 0,
			"damageFromPlayer_basic": 6048,
			"damageFromPlayer_skill": 12039,
			"damageFromPlayer_itemSkill": 639,
			"damageFromPlayer_direct": 1995,
			"damageFromPlayer_uniqueSkill": 0,
			"damageToMonster": 24333,
			"damageToMonster_trap": 0,
			"damageToMonster_basic": 1704,
			"damageToMonster_skill": 22198,
			"damageToMonster_itemSkill": 431,
			"damageToMonster_direct": 0,
			"damageToMonster_uniqueSkill": 0,
			"damageFromMonster": 405,
			"killMonsters": {
				"11": 28,
				"4": 3,
				"5": 4,
				"9": 1
			},
			"healAmount": 13380,
			"teamRecover": 0,
			"protectAbsorb": 3767,
			"addSurveillanceCamera": 0,
			"addTelephotoCamera": 2,
			"removeSurveillanceCamera": 0,
			"removeTelephotoCamera": 0,
			"useHyperLoop": 16,
			"useSecurityConsole": 0,
			"giveUp": 0,
			"teamSpectator": 0,
			"routeIdOfStart": 0,
			"routeSlotId": 0,
			"placeOfStart": "160",
			"matchSize": 8,
			"teamKill": 27,
			"totalFieldKill": 27,
			"accountLevel": 260,
			"killerUserNum": 3206374,
			"killer": "player",
			"killDetail": "킹갓",
			"causeOfDeath": "basicAttack",
			"placeOfDeath": "2030",
			"killerCharacter": "Aiden",
			"killerWeapon": "TwoHandSword",
			"killerUserNum2": 3206374,
			"killer2": "player",
			"killDetail2": "킹갓",
			"causeOfDeath2": "basicAttack",
			"placeOfDeath2": "2050",
			"killerCharacter2": "Aiden",
			"killerWeapon2": "TwoHandSword",
			"killerUserNum3": 609056,
			"killer3": "player",
			"killDetail3": "여긴내자리야",
			"causeOfDeath3": "데비 Q - 하드 슬래시",
			"placeOfDeath3": "2010",
			"killerCharacter3": "DebiMarlene",
			"killerWeapon3": "TwoHandSword",
			"fishingCount": 0,
			"useEmoticonCount": 13,
			"expireDtm": "2023-12-07T23:20:00.000+0900",
			"traitFirstCore": 7000501,
			"traitFirstSub": [],
			"traitSecondSub": [
				7920703,
				7900803,
				7923203
			],
			"airSupplyOpenCount": [
				0,
				0,
				0,
				0,
				0,
				0,
				0
			],
			"foodCraftCount": [
				0,
				0,
				0,
				0,
				0,
				0,
				0
			],
			"beverageCraftCount": [
				0,
				0,
				0,
				0,
				0,
				0,
				0
			],
			"rankPoint": 0,
			"totalTurbineTakeOver": 9,
			"startingItems": [
				113405,
				202307,
				201410,
				203403,
				204406
			],
			"usedNormalHealPack": 0,
			"usedReinforcedHealPack": 0,
			"usedNormalShieldPack": 6,
			"usedReinforceShieldPack": 0,
			"totalVFCredits": [
				30,
				62,
				50,
				69,
				89,
				58,
				76,
				35,
				55,
				54,
				83,
				43,
				9,
				0,
				0,
				0,
				0,
				0,
				0,
				0
			],
			"usedVFCredits": [
				29,
				29,
				36,
				0,
				0,
				235,
				90,
				0,
				90,
				0,
				120,
				0,
				0,
				0,
				0,
				0,
				0,
				0,
				0,
				0
			],
			"sumTotalVFCredits": 713,
			"sumUsedVFCredits": 629,
			"finalInfusion": [
				46,
				24,
				88
			],
			"craftMythic": 0,
			"playerDeaths": 6,
			"killGamma": false,
			"scoredPoint": [
				0,
				0,
				1,
				0,
				2,
				0,
				1,
				2,
				3,
				0,
				1,
				1,
				1,
				0,
				0,
				0,
				0,
				0,
				0,
				0
			],
			"killDetails": "{\"46\":2,\"27\":1,\"65\":1,\"2\":1}",
			"deathDetails": "{\"46\":5,\"65\":1}",
			"killsPhaseOne": 1,
			"killsPhaseTwo": 1,
			"killsPhaseThree": 3,
			"deathsPhaseOne": 2,
			"deathsPhaseTwo": 1,
			"deathsPhaseThree": 3,
			"usedPairLoop": 16,
			"ccTimeToPlayer": 16.933334,
			"creditSource": {
				"PhaseStart": 25.0,
				"StartItem": 5.0,
				"Infusion": 200.0,
				"InfusionReroll": 24.0,
				"KillDrone": 84.0,
				"KillMutantWildDog": 26.0,
				"KillMutantWolf": 36.0,
				"TimeElapsed": 180.0,
				"KillMutantBoar": 24.0,
				"KillAssist": 72.0,
				"KillPlayerMerge": 86.0,
				"InfusionStore": 330.0,
				"ItemShredder": 118.0,
				"KillMutantBear": 12.0,
				"KillOmega": 45.0,
				"InfusionRelic": 75.0
			},
			"boughtInfusion": "{\"44\":1,\"22\":1,\"10001\":11,\"88\":1,\"2003\":1,\"23\":1,\"24\":1,\"45\":1,\"46\":1}",
			"itemTransferredConsole": [],
			"itemTransferredDrone": [],
			"afk": false,
			"escapeState": 0,
			"totalDoubleKill": 0,
			"totalTripleKill": 0,
			"totalQuadraKill": 0,
			"totalExtraKill": 0,
			"collectItemForLog": [
				0,
				0,
				0,
				0,
				0,
				0,
				0
			],
			"equipFirstItemForLog": {
				"0": [
					113405
				],
				"1": [
					202307
				],
				"2": [
					201410
				],
				"3": [
					203403
				],
				"4": [
					204406
				]
			},
			"battleZone1AreaCode": 0,
			"battleZone1BattleMark": 0,
			"battleZone1ItemCode": [],
			"battleZone2AreaCode": 0,
			"battleZone2BattleMark": 0,
			"battleZone2ItemCode": [],
			"battleZone3AreaCode": 0,
			"battleZone3BattleMark": 0,
			"battleZone3ItemCode": [],
			"battleZonePlayerKill": 0,
			"battleZoneDeaths": 0,
			"battleZone1Winner": 0,
			"battleZone2Winner": 0,
			"battleZone3Winner": 0,
			"battleZone1BattleMarkCount": 0,
			"battleZone2BattleMarkCount": 0,
			"battleZone3BattleMarkCount": 0,
			"tacticalSkillGroup": 500050,
			"tacticalSkillLevel": 1,
			"totalGainVFCredit": 713,
			"killPlayerGainVFCredit": 86,
			"killChickenGainVFCredit": 0,
			"killBoarGainVFCredit": 24,
			"killWildDogGainVFCredit": 26,
			"killWolfGainVFCredit": 36,
			"killBearGainVFCredit": 12,
			"killOmegaGainVFCredit": 45,
			"killBatGainVFCredit": 0,
			"killWicklineGainVFCredit": 0,
			"killAlphaGainVFCredit": 0,
			"killItemBountyGainVFCredit": 0,
			"killDroneGainVFCredit": 84,
			"killGammaGainVFCredit": 0,
			"killTurretGainVFCredit": 0,
			"itemShredderGainVFCredit": 118,
			"totalUseVFCredit": 629,
			"remoteDroneUseVFCreditMySelf": 0,
			"remoteDroneUseVFCreditAlly": 0,
			"transferConsoleFromMaterialUseVFCredit": 0,
			"transferConsoleFromEscapeKeyUseVFCredit": 0,
			"transferConsoleFromRevivalUseVFCredit": 0,
			"tacticalSkillUpgradeUseVFCredit": 0,
			"infusionReRollUseVFCredit": 24,
			"infusionTraitUseVFCredit": 200,
			"infusionRelicUseVFCredit": 75,
			"infusionStoreUseVFCredit": 330,
			"teamElimination": 0,
			"teamDown": 27,
			"teamBattleZoneDown": 0,
			"teamRepeatDown": 0,
			"adaptiveForce": 0,
			"adaptiveForceAttack": 0,
			"adaptiveForceAmplify": 0,
			"skillAmp": 778,
			"campFireCraftUncommon": 0,
			"campFireCraftRare": 0,
			"campFireCraftEpic": 0,
			"campFireCraftLegendary": 0,
			"cobaltRandomPickRemoveCharacter": 38,
			"tacticalSkillUseCount": 6,
			"creditRevivalCount": 0,
			"creditRevivedOthersCount": 0,
			"timeSpentInBriefingRoom": 0,
			"IsLeavingBeforeCreditRevivalTerminate": false,
			"crGetAnimal": 129,
			"crGetMutant": 98,
			"crGetPhaseStart": 25,
			"crGetKill": 86,
			"crGetAssist": 72,
			"crGetTimeElapsed": 180,
			"crGetCreditBonus": 0,
			"crUseRemoteDrone": 0,
			"crUseUpgradeTacticalSkill": 0,
			"crUseTreeOfLife": 0,
			"crUseMeteorite": 0,
			"crUseMythril": 0,
			"crUseForceCore": 0,
			"crUseVFBloodSample": 0,
			"crUseActivationModule": 0,
			"crUseRootkit": 0,
			"mmrGainInGame": 0,
			"isLeavingBeforeCreditRevivalTerminate": false
		},
		{
			"userNum": 1092125,
			"nickname": "혁진이등장",
			"gameId": 27619566,
			"seasonId": 0,
			"matchingMode": 6,
			"matchingTeamMode": 4,
			"characterNum": 50,
			"skinCode": 1050003,
			"characterLevel": 20,
			"gameRank": 1,
			"playerKill": 7,
			"playerAssistant": 10,
			"monsterKill": 33,
			"bestWeapon": 21,
			"bestWeaponLevel": 18,
			"masteryLevel": {
				"21": 18,
				"201": 20,
				"202": 6,
				"101": 6,
				"102": 6,
				"103": 6
			},
			"equipment": {
				"0": 120402,
				"1": 202501,
				"2": 201411,
				"3": 203510,
				"4": 204413
			},
			"versionMajor": 3,
			"versionMinor": 0,
			"language": "Korean",
			"skillLevelInfo": {
				"1050300": 4,
				"1050200": 5,
				"1050400": 5,
				"1050500": 3,
				"1050100": 2,
				"3021000": 2,
				"1050310": 1
			},
			"skillOrderInfo": {
				"1": 1050300,
				"2": 1050200,
				"3": 1050400,
				"4": 1050500,
				"5": 1050100,
				"6": 1050100,
				"7": 1050200,
				"8": 1050200,
				"9": 1050200,
				"10": 1050200,
				"11": 1050500,
				"12": 3021000,
				"13": 1050300,
				"14": 1050300,
				"15": 1050310,
				"16": 1050400,
				"17": 1050500,
				"18": 3021000,
				"19": 1050400,
				"20": 1050300,
				"21": 1050400,
				"22": 1050400
			},
			"serverName": "Seoul",
			"maxHp": 2678,
			"maxSp": 1313,
			"attackPower": 163,
			"defense": 160,
			"hpRegen": 8.42,
			"spRegen": 16.72,
			"attackSpeed": 1.07,
			"moveSpeed": 4.13,
			"outOfCombatMoveSpeed": 4.13,
			"sightRange": 11.0,
			"attackRange": 1.65,
			"criticalStrikeChance": 0.0,
			"criticalStrikeDamage": 15.000001,
			"coolDownReduction": 40.0,
			"lifeSteal": 0.4,
			"normalLifeSteal": 0.0,
			"skillLifeSteal": 0.0,
			"amplifierToMonster": 12.0,
			"trapDamage": 0.0,
			"bonusCoin": 0,
			"gainExp": 120,
			"baseExp": 120,
			"bonusExp": 0,
			"startDtm": "2023-09-08T23:07:33.033+0900",
			"duration": 746,
			"playTime": 741,
			"watchTime": 0,
			"totalTime": 741,
			"survivableTime": 25,
			"botAdded": 0,
			"botRemain": 0,
			"restrictedAreaAccelerated": 0,
			"safeAreas": 0,
			"teamNumber": 1,
			"preMade": 2,
			"eventMissionResult": {},
			"gainedNormalMmrKFactor": 20.0,
			"victory": 1,
			"craftUncommon": 0,
			"craftRare": 0,
			"craftEpic": 0,
			"craftLegend": 0,
			"damageToPlayer": 24487,
			"damageToPlayer_trap": 0,
			"damageToPlayer_basic": 739,
			"damageToPlayer_skill": 22924,
			"damageToPlayer_itemSkill": 48,
			"damageToPlayer_direct": 776,
			"damageToPlayer_uniqueSkill": 0,
			"damageFromPlayer": 31004,
			"damageFromPlayer_trap": 0,
			"damageFromPlayer_basic": 8110,
			"damageFromPlayer_skill": 14407,
			"damageFromPlayer_itemSkill": 639,
			"damageFromPlayer_direct": 7848,
			"damageFromPlayer_uniqueSkill": 0,
			"damageToMonster": 22516,
			"damageToMonster_trap": 0,
			"damageToMonster_basic": 1550,
			"damageToMonster_skill": 20550,
			"damageToMonster_itemSkill": 27,
			"damageToMonster_direct": 389,
			"damageToMonster_uniqueSkill": 0,
			"damageFromMonster": 1038,
			"killMonsters": {
				"4": 5,
				"3": 4,
				"5": 4,
				"11": 20
			},
			"healAmount": 15866,
			"teamRecover": 1090,
			"protectAbsorb": 3561,
			"addSurveillanceCamera": 0,
			"addTelephotoCamera": 2,
			"removeSurveillanceCamera": 0,
			"removeTelephotoCamera": 1,
			"useHyperLoop": 10,
			"useSecurityConsole": 0,
			"giveUp": 0,
			"teamSpectator": 0,
			"routeIdOfStart": 0,
			"routeSlotId": 0,
			"placeOfStart": "160",
			"matchSize": 8,
			"teamKill": 27,
			"totalFieldKill": 27,
			"accountLevel": 294,
			"killerUserNum": 609056,
			"killer": "player",
			"killDetail": "여긴내자리야",
			"causeOfDeath": "데비 W - 휠 댄스",
			"placeOfDeath": "2010",
			"killerCharacter": "DebiMarlene",
			"killerWeapon": "TwoHandSword",
			"killerUserNum2": 609056,
			"killer2": "player",
			"killDetail2": "여긴내자리야",
			"causeOfDeath2": "",
			"placeOfDeath2": "2010",
			"killerCharacter2": "DebiMarlene",
			"killerWeapon2": "TwoHandSword",
			"killerUserNum3": 609056,
			"killer3": "player",
			"killDetail3": "여긴내자리야",
			"causeOfDeath3": "데비 W - 휠 댄스",
			"placeOfDeath3": "2030",
			"killerCharacter3": "DebiMarlene",
			"killerWeapon3": "TwoHandSword",
			"fishingCount": 0,
			"useEmoticonCount": 16,
			"expireDtm": "2023-12-07T23:20:00.000+0900",
			"traitFirstCore": 7000501,
			"traitFirstSub": [],
			"traitSecondSub": [
				7921703,
				7922402,
				7920703
			],
			"airSupplyOpenCount": [
				0,
				0,
				0,
				0,
				0,
				0,
				0
			],
			"foodCraftCount": [
				0,
				0,
				0,
				0,
				0,
				0,
				0
			],
			"beverageCraftCount": [
				0,
				0,
				0,
				0,
				0,
				0,
				0
			],
			"rankPoint": 0,
			"totalTurbineTakeOver": 2,
			"startingItems": [
				120406,
				202419,
				201412,
				203410,
				204406
			],
			"usedNormalHealPack": 10,
			"usedReinforcedHealPack": 0,
			"usedNormalShieldPack": 7,
			"usedReinforceShieldPack": 0,
			"totalVFCredits": [
				25,
				47,
				47,
				53,
				104,
				56,
				39,
				58,
				45,
				62,
				37,
				34,
				14,
				0,
				0,
				0,
				0,
				0,
				0,
				0
			],
			"usedVFCredits": [
				20,
				0,
				60,
				60,
				30,
				108,
				35,
				80,
				0,
				55,
				85,
				38,
				0,
				0,
				0,
				0,
				0,
				0,
				0,
				0
			],
			"sumTotalVFCredits": 621,
			"sumUsedVFCredits": 571,
			"finalInfusion": [
				68,
				74,
				46
			],
			"craftMythic": 0,
			"playerDeaths": 7,
			"killGamma": false,
			"scoredPoint": [
				0,
				0,
				2,
				0,
				1,
				0,
				1,
				0,
				1,
				1,
				0,
				0,
				1,
				0,
				0,
				0,
				0,
				0,
				0,
				0
			],
			"killDetails": "{\"27\":2,\"65\":3,\"2\":2}",
			"deathDetails": "{\"65\":4,\"2\":1,\"27\":2}",
			"killsPhaseOne": 2,
			"killsPhaseTwo": 2,
			"killsPhaseThree": 3,
			"deathsPhaseOne": 1,
			"deathsPhaseTwo": 3,
			"deathsPhaseThree": 3,
			"usedPairLoop": 10,
			"ccTimeToPlayer": 31.733335,
			"creditSource": {
				"PhaseStart": 25.0,
				"Infusion": 185.0,
				"KillMutantWildDog": 30.0,
				"KillMutantWolf": 36.0,
				"TimeElapsed": 180.0,
				"KillMutantBoar": 40.0,
				"KillPlayerMerge": 92.0,
				"InfusionStore": 308.0,
				"ItemShredder": 76.0,
				"KillMutantBear": 12.0,
				"KillDrone": 60.0,
				"KillOmega": 30.0,
				"InfusionRelic": 75.0,
				"InfusionReroll": 3.0,
				"KillAssist": 40.0
			},
			"boughtInfusion": "{\"79\":1,\"10001\":10,\"2002\":1,\"74\":1,\"44\":1,\"45\":1,\"46\":1,\"67\":1,\"68\":1,\"1001\":1}",
			"itemTransferredConsole": [],
			"itemTransferredDrone": [],
			"afk": false,
			"escapeState": 0,
			"totalDoubleKill": 0,
			"totalTripleKill": 0,
			"totalQuadraKill": 0,
			"totalExtraKill": 0,
			"collectItemForLog": [
				0,
				0,
				0,
				0,
				0,
				0,
				0
			],
			"equipFirstItemForLog": {
				"0": [
					120406
				],
				"1": [
					202419
				],
				"2": [
					201412
				],
				"3": [
					203410
				],
				"4": [
					204406
				]
			},
			"battleZone1AreaCode": 0,
			"battleZone1BattleMark": 0,
			"battleZone1ItemCode": [],
			"battleZone2AreaCode": 0,
			"battleZone2BattleMark": 0,
			"battleZone2ItemCode": [],
			"battleZone3AreaCode": 0,
			"battleZone3BattleMark": 0,
			"battleZone3ItemCode": [],
			"battleZonePlayerKill": 0,
			"battleZoneDeaths": 0,
			"battleZone1Winner": 0,
			"battleZone2Winner": 0,
			"battleZone3Winner": 0,
			"battleZone1BattleMarkCount": 0,
			"battleZone2BattleMarkCount": 0,
			"battleZone3BattleMarkCount": 0,
			"tacticalSkillGroup": 500040,
			"tacticalSkillLevel": 1,
			"totalGainVFCredit": 621,
			"killPlayerGainVFCredit": 92,
			"killChickenGainVFCredit": 0,
			"killBoarGainVFCredit": 40,
			"killWildDogGainVFCredit": 30,
			"killWolfGainVFCredit": 36,
			"killBearGainVFCredit": 12,
			"killOmegaGainVFCredit": 30,
			"killBatGainVFCredit": 0,
			"killWicklineGainVFCredit": 0,
			"killAlphaGainVFCredit": 0,
			"killItemBountyGainVFCredit": 0,
			"killDroneGainVFCredit": 60,
			"killGammaGainVFCredit": 0,
			"killTurretGainVFCredit": 0,
			"itemShredderGainVFCredit": 76,
			"totalUseVFCredit": 571,
			"remoteDroneUseVFCreditMySelf": 0,
			"remoteDroneUseVFCreditAlly": 0,
			"transferConsoleFromMaterialUseVFCredit": 0,
			"transferConsoleFromEscapeKeyUseVFCredit": 0,
			"transferConsoleFromRevivalUseVFCredit": 0,
			"tacticalSkillUpgradeUseVFCredit": 0,
			"infusionReRollUseVFCredit": 3,
			"infusionTraitUseVFCredit": 185,
			"infusionRelicUseVFCredit": 75,
			"infusionStoreUseVFCredit": 308,
			"teamElimination": 0,
			"teamDown": 27,
			"teamBattleZoneDown": 0,
			"teamRepeatDown": 0,
			"adaptiveForce": 45,
			"adaptiveForceAttack": 45,
			"adaptiveForceAmplify": 187,
			"skillAmp": 919,
			"campFireCraftUncommon": 0,
			"campFireCraftRare": 0,
			"campFireCraftEpic": 0,
			"campFireCraftLegendary": 0,
			"cobaltRandomPickRemoveCharacter": 37,
			"tacticalSkillUseCount": 20,
			"creditRevivalCount": 0,
			"creditRevivedOthersCount": 0,
			"timeSpentInBriefingRoom": 0,
			"IsLeavingBeforeCreditRevivalTerminate": false,
			"crGetAnimal": 90,
			"crGetMutant": 118,
			"crGetPhaseStart": 25,
			"crGetKill": 92,
			"crGetAssist": 40,
			"crGetTimeElapsed": 180,
			"crGetCreditBonus": 0,
			"crUseRemoteDrone": 0,
			"crUseUpgradeTacticalSkill": 0,
			"crUseTreeOfLife": 0,
			"crUseMeteorite": 0,
			"crUseMythril": 0,
			"crUseForceCore": 0,
			"crUseVFBloodSample": 0,
			"crUseActivationModule": 0,
			"crUseRootkit": 0,
			"mmrGainInGame": 0,
			"isLeavingBeforeCreditRevivalTerminate": false
		},
		{
			"userNum": 609056,
			"nickname": "여긴내자리야",
			"gameId": 27619566,
			"seasonId": 0,
			"matchingMode": 6,
			"matchingTeamMode": 4,
			"characterNum": 65,
			"skinCode": 1065000,
			"characterLevel": 19,
			"gameRank": 2,
			"playerKill": 6,
			"playerAssistant": 8,
			"monsterKill": 14,
			"bestWeapon": 16,
			"bestWeaponLevel": 18,
			"masteryLevel": {
				"16": 18,
				"201": 20,
				"202": 6,
				"101": 6,
				"102": 6,
				"103": 6
			},
			"equipment": {
				"0": 602409,
				"1": 202507,
				"2": 201509,
				"3": 203503,
				"4": 204501
			},
			"versionMajor": 3,
			"versionMinor": 0,
			"language": "Korean",
			"skillLevelInfo": {
				"1065500": 3,
				"1065300": 3,
				"1065200": 4,
				"1065100": 2,
				"1065400": 3,
				"1065410": 1,
				"3016000": 2,
				"1065310": 2
			},
			"skillOrderInfo": {
				"1": 1065500,
				"2": 1065300,
				"3": 1065200,
				"4": 1065100,
				"5": 1065100,
				"6": 1065400,
				"7": 1065400,
				"8": 1065400,
				"9": 1065410,
				"10": 1065500,
				"11": 3016000,
				"12": 1065200,
				"13": 1065310,
				"14": 1065300,
				"15": 1065300,
				"16": 1065500,
				"17": 3016000,
				"18": 1065310,
				"19": 1065200,
				"20": 1065200
			},
			"serverName": "Seoul",
			"maxHp": 2696,
			"maxSp": 718,
			"attackPower": 237,
			"defense": 208,
			"hpRegen": 3.42,
			"spRegen": 4.7,
			"attackSpeed": 1.32,
			"moveSpeed": 3.89,
			"outOfCombatMoveSpeed": 3.89,
			"sightRange": 9.0,
			"attackRange": 2.05,
			"criticalStrikeChance": 0.0,
			"criticalStrikeDamage": 0.0,
			"coolDownReduction": 0.0,
			"lifeSteal": 0.0,
			"normalLifeSteal": 0.0,
			"skillLifeSteal": 0.0,
			"amplifierToMonster": 12.0,
			"trapDamage": 0.0,
			"bonusCoin": 0,
			"gainExp": 79,
			"baseExp": 79,
			"bonusExp": 0,
			"startDtm": "2023-09-08T23:07:33.033+0900",
			"duration": 746,
			"playTime": 741,
			"watchTime": 0,
			"totalTime": 741,
			"survivableTime": 25,
			"botAdded": 0,
			"botRemain": 0,
			"restrictedAreaAccelerated": 0,
			"safeAreas": 0,
			"teamNumber": 2,
			"preMade": 1,
			"eventMissionResult": {},
			"gainedNormalMmrKFactor": 20.0,
			"victory": 0,
			"craftUncommon": 0,
			"craftRare": 0,
			"craftEpic": 0,
			"craftLegend": 0,
			"damageToPlayer": 30490,
			"damageToPlayer_trap": 0,
			"damageToPlayer_basic": 3998,
			"damageToPlayer_skill": 15368,
			"damageToPlayer_itemSkill": 0,
			"damageToPlayer_direct": 11124,
			"damageToPlayer_uniqueSkill": 0,
			"damageFromPlayer": 26364,
			"damageFromPlayer_trap": 0,
			"damageFromPlayer_basic": 1654,
			"damageFromPlayer_skill": 22863,
			"damageFromPlayer_itemSkill": 1103,
			"damageFromPlayer_direct": 744,
			"damageFromPlayer_uniqueSkill": 0,
			"damageToMonster": 11412,
			"damageToMonster_trap": 0,
			"damageToMonster_basic": 2553,
			"damageToMonster_skill": 6733,
			"damageToMonster_itemSkill": 0,
			"damageToMonster_direct": 2126,
			"damageToMonster_uniqueSkill": 0,
			"damageFromMonster": 2053,
			"killMonsters": {
				"1": 1,
				"4": 1,
				"3": 2,
				"5": 4,
				"6": 1,
				"11": 5
			},
			"healAmount": 12767,
			"teamRecover": 0,
			"protectAbsorb": 3459,
			"addSurveillanceCamera": 0,
			"addTelephotoCamera": 2,
			"removeSurveillanceCamera": 0,
			"removeTelephotoCamera": 0,
			"useHyperLoop": 10,
			"useSecurityConsole": 0,
			"giveUp": 0,
			"teamSpectator": 0,
			"routeIdOfStart": 0,
			"routeSlotId": 0,
			"placeOfStart": "160",
			"matchSize": 8,
			"teamKill": 21,
			"totalFieldKill": 21,
			"accountLevel": 120,
			"killerUserNum": 1092125,
			"killer": "player",
			"killDetail": "혁진이등장",
			"causeOfDeath": "basicAttack",
			"placeOfDeath": "2010",
			"killerCharacter": "Elena",
			"killerWeapon": "Rapier",
			"killerUserNum2": 2582943,
			"killer2": "player",
			"killDetail2": "티잔",
			"causeOfDeath2": "basicAttack",
			"placeOfDeath2": "2020",
			"killerCharacter2": "Haze",
			"killerWeapon2": "AssaultRifle",
			"killerUserNum3": 1736707,
			"killer3": "player",
			"killDetail3": "샌토바보아니다",
			"causeOfDeath3": "윌슨! 도와줘",
			"placeOfDeath3": "2030",
			"killerCharacter3": "Sissela",
			"killerWeapon3": "DirectFire",
			"fishingCount": 0,
			"useEmoticonCount": 14,
			"expireDtm": "2023-12-07T23:20:00.000+0900",
			"traitFirstCore": 7000401,
			"traitFirstSub": [],
			"traitSecondSub": [
				7900303,
				7900203,
				7922302
			],
			"airSupplyOpenCount": [
				0,
				0,
				0,
				0,
				0,
				0,
				0
			],
			"foodCraftCount": [
				0,
				0,
				0,
				0,
				0,
				0,
				0
			],
			"beverageCraftCount": [
				0,
				0,
				0,
				0,
				0,
				0,
				0
			],
			"rankPoint": 0,
			"totalTurbineTakeOver": 3,
			"startingItems": [
				102407,
				202404,
				201409,
				203409,
				204411
			],
			"usedNormalHealPack": 5,
			"usedReinforcedHealPack": 0,
			"usedNormalShieldPack": 6,
			"usedReinforceShieldPack": 1,
			"totalVFCredits": [
				62,
				55,
				58,
				71,
				48,
				28,
				90,
				43,
				43,
				21,
				23,
				23,
				6,
				0,
				0,
				0,
				0,
				0,
				0,
				0
			],
			"usedVFCredits": [
				60,
				0,
				60,
				90,
				50,
				0,
				120,
				65,
				0,
				55,
				0,
				0,
				30,
				0,
				0,
				0,
				0,
				0,
				0,
				0
			],
			"sumTotalVFCredits": 571,
			"sumUsedVFCredits": 530,
			"finalInfusion": [
				9,
				6,
				73
			],
			"craftMythic": 0,
			"playerDeaths": 7,
			"killGamma": false,
			"scoredPoint": [
				0,
				1,
				0,
				1,
				1,
				1,
				2,
				0,
				0,
				1,
				0,
				2,
				0,
				0,
				0,
				0,
				0,
				0,
				0,
				0
			],
			"killDetails": "{\"50\":4,\"15\":1,\"47\":1}",
			"deathDetails": "{\"50\":3,\"58\":2,\"15\":1,\"47\":1}",
			"killsPhaseOne": 1,
			"killsPhaseTwo": 4,
			"killsPhaseThree": 1,
			"deathsPhaseOne": 1,
			"deathsPhaseTwo": 1,
			"deathsPhaseThree": 5,
			"usedPairLoop": 10,
			"ccTimeToPlayer": 24.033335,
			"creditSource": {
				"PhaseStart": 25.0,
				"StartItem": 25.0,
				"InfusionStore": 360.0,
				"ItemShredder": 120.0,
				"KillMutantWildDog": 10.0,
				"KillMutantBoar": 24.0,
				"TimeElapsed": 182.0,
				"KillMutantWolf": 24.0,
				"KillPlayerMerge": 65.0,
				"KillMutantBear": 49.0,
				"Infusion": 170.0,
				"KillAssist": 32.0,
				"KillDrone": 15.0
			},
			"boughtInfusion": "{\"10001\":12,\"7\":1,\"4\":1,\"79\":1,\"8\":1,\"9\":1,\"5\":1,\"6\":1}",
			"itemTransferredConsole": [],
			"itemTransferredDrone": [],
			"afk": false,
			"escapeState": 0,
			"totalDoubleKill": 0,
			"totalTripleKill": 0,
			"totalQuadraKill": 0,
			"totalExtraKill": 0,
			"collectItemForLog": [
				0,
				0,
				0,
				0,
				0,
				0,
				0
			],
			"equipFirstItemForLog": {
				"0": [
					102407
				],
				"1": [
					202404
				],
				"2": [
					201409
				],
				"3": [
					203409
				],
				"4": [
					204411
				]
			},
			"battleZone1AreaCode": 0,
			"battleZone1BattleMark": 0,
			"battleZone1ItemCode": [],
			"battleZone2AreaCode": 0,
			"battleZone2BattleMark": 0,
			"battleZone2ItemCode": [],
			"battleZone3AreaCode": 0,
			"battleZone3BattleMark": 0,
			"battleZone3ItemCode": [],
			"battleZonePlayerKill": 0,
			"battleZoneDeaths": 0,
			"battleZone1Winner": 0,
			"battleZone2Winner": 0,
			"battleZone3Winner": 0,
			"battleZone1BattleMarkCount": 0,
			"battleZone2BattleMarkCount": 0,
			"battleZone3BattleMarkCount": 0,
			"tacticalSkillGroup": 500110,
			"tacticalSkillLevel": 1,
			"totalGainVFCredit": 571,
			"killPlayerGainVFCredit": 65,
			"killChickenGainVFCredit": 0,
			"killBoarGainVFCredit": 24,
			"killWildDogGainVFCredit": 10,
			"killWolfGainVFCredit": 24,
			"killBearGainVFCredit": 49,
			"killOmegaGainVFCredit": 0,
			"killBatGainVFCredit": 0,
			"killWicklineGainVFCredit": 0,
			"killAlphaGainVFCredit": 0,
			"killItemBountyGainVFCredit": 0,
			"killDroneGainVFCredit": 15,
			"killGammaGainVFCredit": 0,
			"killTurretGainVFCredit": 0,
			"itemShredderGainVFCredit": 120,
			"totalUseVFCredit": 530,
			"remoteDroneUseVFCreditMySelf": 0,
			"remoteDroneUseVFCreditAlly": 0,
			"transferConsoleFromMaterialUseVFCredit": 0,
			"transferConsoleFromEscapeKeyUseVFCredit": 0,
			"transferConsoleFromRevivalUseVFCredit": 0,
			"tacticalSkillUpgradeUseVFCredit": 0,
			"infusionReRollUseVFCredit": 0,
			"infusionTraitUseVFCredit": 170,
			"infusionRelicUseVFCredit": 0,
			"infusionStoreUseVFCredit": 360,
			"teamElimination": 0,
			"teamDown": 21,
			"teamBattleZoneDown": 0,
			"teamRepeatDown": 0,
			"adaptiveForce": 0,
			"adaptiveForceAttack": 0,
			"adaptiveForceAmplify": 0,
			"skillAmp": 0,
			"campFireCraftUncommon": 0,
			"campFireCraftRare": 0,
			"campFireCraftEpic": 0,
			"campFireCraftLegendary": 0,
			"cobaltRandomPickRemoveCharacter": 24,
			"tacticalSkillUseCount": 14,
			"creditRevivalCount": 0,
			"creditRevivedOthersCount": 0,
			"timeSpentInBriefingRoom": 0,
			"IsLeavingBeforeCreditRevivalTerminate": false,
			"crGetAnimal": 15,
			"crGetMutant": 107,
			"crGetPhaseStart": 25,
			"crGetKill": 65,
			"crGetAssist": 32,
			"crGetTimeElapsed": 182,
			"crGetCreditBonus": 0,
			"crUseRemoteDrone": 0,
			"crUseUpgradeTacticalSkill": 0,
			"crUseTreeOfLife": 0,
			"crUseMeteorite": 0,
			"crUseMythril": 0,
			"crUseForceCore": 0,
			"crUseVFBloodSample": 0,
			"crUseActivationModule": 0,
			"crUseRootkit": 0,
			"mmrGainInGame": 0,
			"isLeavingBeforeCreditRevivalTerminate": false
		},
		{
			"userNum": 411349,
			"nickname": "우엉은맛있우엉",
			"gameId": 27619566,
			"seasonId": 0,
			"matchingMode": 6,
			"matchingTeamMode": 4,
			"characterNum": 2,
			"skinCode": 1002002,
			"characterLevel": 19,
			"gameRank": 2,
			"playerKill": 3,
			"playerAssistant": 13,
			"monsterKill": 23,
			"bestWeapon": 11,
			"bestWeaponLevel": 16,
			"masteryLevel": {
				"9": 6,
				"10": 6,
				"11": 16,
				"201": 18,
				"202": 6,
				"101": 6,
				"102": 6,
				"103": 6
			},
			"equipment": {
				"0": 118501,
				"1": 202502,
				"2": 201411,
				"3": 203510,
				"4": 204504
			},
			"versionMajor": 3,
			"versionMinor": 0,
			"language": "Korean",
			"skillLevelInfo": {
				"1002200": 5,
				"1002300": 5,
				"1002400": 5,
				"1002500": 3,
				"3011000": 2,
				"1002100": 1
			},
			"skillOrderInfo": {
				"1": 1002200,
				"2": 1002300,
				"3": 1002400,
				"4": 1002500,
				"5": 1002200,
				"6": 1002300,
				"7": 1002200,
				"8": 1002300,
				"9": 1002200,
				"10": 1002300,
				"11": 1002500,
				"12": 1002200,
				"13": 3011000,
				"14": 1002300,
				"15": 1002400,
				"16": 1002400,
				"17": 1002500,
				"18": 1002400,
				"19": 3011000,
				"20": 1002400,
				"21": 1002100
			},
			"serverName": "Seoul",
			"maxHp": 2153,
			"maxSp": 1417,
			"attackPower": 169,
			"defense": 116,
			"hpRegen": 3.66,
			"spRegen": 6.01,
			"attackSpeed": 0.85,
			"moveSpeed": 4.15,
			"outOfCombatMoveSpeed": 4.15,
			"sightRange": 11.5,
			"attackRange": 6.4,
			"criticalStrikeChance": 67.0,
			"criticalStrikeDamage": -1.0,
			"coolDownReduction": 32.0,
			"lifeSteal": 0.12,
			"normalLifeSteal": 0.0,
			"skillLifeSteal": 0.0,
			"amplifierToMonster": 12.0,
			"trapDamage": 0.0,
			"bonusCoin": 0,
			"gainExp": 79,
			"baseExp": 79,
			"bonusExp": 0,
			"startDtm": "2023-09-08T23:07:33.033+0900",
			"duration": 746,
			"playTime": 741,
			"watchTime": 0,
			"totalTime": 741,
			"survivableTime": 25,
			"botAdded": 0,
			"botRemain": 0,
			"restrictedAreaAccelerated": 0,
			"safeAreas": 0,
			"teamNumber": 2,
			"preMade": 1,
			"eventMissionResult": {},
			"gainedNormalMmrKFactor": 20.0,
			"victory": 0,
			"craftUncommon": 0,
			"craftRare": 0,
			"craftEpic": 0,
			"craftLegend": 0,
			"damageToPlayer": 22540,
			"damageToPlayer_trap": 0,
			"damageToPlayer_basic": 2472,
			"damageToPlayer_skill": 18732,
			"damageToPlayer_itemSkill": 1336,
			"damageToPlayer_direct": 0,
			"damageToPlayer_uniqueSkill": 0,
			"damageFromPlayer": 25031,
			"damageFromPlayer_trap": 0,
			"damageFromPlayer_basic": 1465,
			"damageFromPlayer_skill": 21361,
			"damageFromPlayer_itemSkill": 854,
			"damageFromPlayer_direct": 1351,
			"damageFromPlayer_uniqueSkill": 0,
			"damageToMonster": 10022,
			"damageToMonster_trap": 0,
			"damageToMonster_basic": 2468,
			"damageToMonster_skill": 7554,
			"damageToMonster_itemSkill": 0,
			"damageToMonster_direct": 0,
			"damageToMonster_uniqueSkill": 0,
			"damageFromMonster": 54,
			"killMonsters": {
				"11": 23
			},
			"healAmount": 9904,
			"teamRecover": 945,
			"protectAbsorb": 5090,
			"addSurveillanceCamera": 0,
			"addTelephotoCamera": 2,
			"removeSurveillanceCamera": 0,
			"removeTelephotoCamera": 0,
			"useHyperLoop": 11,
			"useSecurityConsole": 0,
			"giveUp": 0,
			"teamSpectator": 0,
			"routeIdOfStart": 0,
			"routeSlotId": 0,
			"placeOfStart": "2080",
			"matchSize": 8,
			"teamKill": 21,
			"totalFieldKill": 21,
			"accountLevel": 124,
			"killerUserNum": 2212773,
			"killer": "player",
			"killDetail": "폴더바보아니다",
			"causeOfDeath": "황혼의 도둑",
			"placeOfDeath": "2030",
			"killerCharacter": "Laura",
			"killerWeapon": "Whip",
			"killerUserNum2": 2212773,
			"killer2": "player",
			"killDetail2": "폴더바보아니다",
			"causeOfDeath2": "네레아의 가르침",
			"placeOfDeath2": "2030",
			"killerCharacter2": "Laura",
			"killerWeapon2": "Whip",
			"killerUserNum3": 1092125,
			"killer3": "player",
			"killDetail3": "혁진이등장",
			"causeOfDeath3": "엘레나 W - 강화",
			"placeOfDeath3": "2030",
			"killerCharacter3": "Elena",
			"killerWeapon3": "Rapier",
			"fishingCount": 0,
			"useEmoticonCount": 3,
			"expireDtm": "2023-12-07T23:20:00.000+0900",
			"traitFirstCore": 7000501,
			"traitFirstSub": [],
			"traitSecondSub": [
				7920702,
				7923203,
				7900803
			],
			"airSupplyOpenCount": [
				0,
				0,
				0,
				0,
				0,
				0,
				0
			],
			"foodCraftCount": [
				0,
				0,
				0,
				0,
				0,
				0,
				0
			],
			"beverageCraftCount": [
				0,
				0,
				0,
				0,
				0,
				0,
				0
			],
			"rankPoint": 0,
			"totalTurbineTakeOver": 2,
			"startingItems": [
				118406,
				202417,
				201405,
				203506,
				204406
			],
			"usedNormalHealPack": 4,
			"usedReinforcedHealPack": 0,
			"usedNormalShieldPack": 8,
			"usedReinforceShieldPack": 0,
			"totalVFCredits": [
				45,
				82,
				48,
				57,
				40,
				29,
				62,
				73,
				45,
				30,
				27,
				27,
				16,
				0,
				0,
				0,
				0,
				0,
				0,
				0
			],
			"usedVFCredits": [
				30,
				50,
				0,
				120,
				30,
				0,
				59,
				137,
				9,
				45,
				0,
				30,
				55,
				0,
				0,
				0,
				0,
				0,
				0,
				0
			],
			"sumTotalVFCredits": 581,
			"sumUsedVFCredits": 565,
			"finalInfusion": [
				45,
				88,
				24
			],
			"craftMythic": 0,
			"playerDeaths": 8,
			"killGamma": false,
			"scoredPoint": [
				0,
				1,
				0,
				0,
				0,
				1,
				3,
				0,
				1,
				0,
				0,
				0,
				0,
				0,
				0,
				0,
				0,
				0,
				0,
				0
			],
			"killDetails": "{\"47\":2,\"50\":1}",
			"deathDetails": "{\"47\":4,\"50\":2,\"15\":1,\"58\":1}",
			"killsPhaseOne": 1,
			"killsPhaseTwo": 1,
			"killsPhaseThree": 1,
			"deathsPhaseOne": 1,
			"deathsPhaseTwo": 2,
			"deathsPhaseThree": 5,
			"usedPairLoop": 11,
			"ccTimeToPlayer": 9.250001,
			"creditSource": {
				"PhaseStart": 25.0,
				"StartItem": 10.0,
				"InfusionStore": 368.0,
				"ItemShredder": 116.0,
				"KillDrone": 69.0,
				"KillMutantWildDog": 8.0,
				"KillMutantBoar": 16.0,
				"TimeElapsed": 182.0,
				"KillMutantWolf": 16.0,
				"KillAssist": 52.0,
				"KillPlayerMerge": 51.0,
				"Infusion": 170.0,
				"KillMutantBear": 36.0,
				"InfusionReroll": 27.0
			},
			"boughtInfusion": "{\"10001\":12,\"44\":1,\"88\":1,\"1001\":1,\"22\":1,\"23\":1,\"24\":1,\"45\":1}",
			"itemTransferredConsole": [],
			"itemTransferredDrone": [],
			"afk": false,
			"escapeState": 0,
			"totalDoubleKill": 0,
			"totalTripleKill": 0,
			"totalQuadraKill": 0,
			"totalExtraKill": 0,
			"collectItemForLog": [
				0,
				0,
				0,
				0,
				0,
				0,
				0
			],
			"equipFirstItemForLog": {
				"0": [
					118406
				],
				"1": [
					202417
				],
				"2": [
					201405
				],
				"3": [
					203506
				],
				"4": [
					204406
				]
			},
			"battleZone1AreaCode": 0,
			"battleZone1BattleMark": 0,
			"battleZone1ItemCode": [],
			"battleZone2AreaCode": 0,
			"battleZone2BattleMark": 0,
			"battleZone2ItemCode": [],
			"battleZone3AreaCode": 0,
			"battleZone3BattleMark": 0,
			"battleZone3ItemCode": [],
			"battleZonePlayerKill": 0,
			"battleZoneDeaths": 0,
			"battleZone1Winner": 0,
			"battleZone2Winner": 0,
			"battleZone3Winner": 0,
			"battleZone1BattleMarkCount": 0,
			"battleZone2BattleMarkCount": 0,
			"battleZone3BattleMarkCount": 0,
			"tacticalSkillGroup": 500110,
			"tacticalSkillLevel": 1,
			"totalGainVFCredit": 581,
			"killPlayerGainVFCredit": 51,
			"killChickenGainVFCredit": 0,
			"killBoarGainVFCredit": 16,
			"killWildDogGainVFCredit": 8,
			"killWolfGainVFCredit": 16,
			"killBearGainVFCredit": 36,
			"killOmegaGainVFCredit": 0,
			"killBatGainVFCredit": 0,
			"killWicklineGainVFCredit": 0,
			"killAlphaGainVFCredit": 0,
			"killItemBountyGainVFCredit": 0,
			"killDroneGainVFCredit": 69,
			"killGammaGainVFCredit": 0,
			"killTurretGainVFCredit": 0,
			"itemShredderGainVFCredit": 116,
			"totalUseVFCredit": 565,
			"remoteDroneUseVFCreditMySelf": 0,
			"remoteDroneUseVFCreditAlly": 0,
			"transferConsoleFromMaterialUseVFCredit": 0,
			"transferConsoleFromEscapeKeyUseVFCredit": 0,
			"transferConsoleFromRevivalUseVFCredit": 0,
			"tacticalSkillUpgradeUseVFCredit": 0,
			"infusionReRollUseVFCredit": 27,
			"infusionTraitUseVFCredit": 170,
			"infusionRelicUseVFCredit": 0,
			"infusionStoreUseVFCredit": 368,
			"teamElimination": 0,
			"teamDown": 21,
			"teamBattleZoneDown": 0,
			"teamRepeatDown": 0,
			"adaptiveForce": 45,
			"adaptiveForceAttack": 39,
			"adaptiveForceAmplify": 158,
			"skillAmp": 725,
			"campFireCraftUncommon": 0,
			"campFireCraftRare": 0,
			"campFireCraftEpic": 0,
			"campFireCraftLegendary": 0,
			"cobaltRandomPickRemoveCharacter": 33,
			"tacticalSkillUseCount": 10,
			"creditRevivalCount": 0,
			"creditRevivedOthersCount": 0,
			"timeSpentInBriefingRoom": 0,
			"IsLeavingBeforeCreditRevivalTerminate": false,
			"crGetAnimal": 69,
			"crGetMutant": 76,
			"crGetPhaseStart": 25,
			"crGetKill": 51,
			"crGetAssist": 52,
			"crGetTimeElapsed": 182,
			"crGetCreditBonus": 0,
			"crUseRemoteDrone": 0,
			"crUseUpgradeTacticalSkill": 0,
			"crUseTreeOfLife": 0,
			"crUseMeteorite": 0,
			"crUseMythril": 0,
			"crUseForceCore": 0,
			"crUseVFBloodSample": 0,
			"crUseActivationModule": 0,
			"crUseRootkit": 0,
			"mmrGainInGame": 0,
			"isLeavingBeforeCreditRevivalTerminate": false
		},
		{
			"userNum": 377032,
			"nickname": "우라라",
			"gameId": 27619566,
			"seasonId": 0,
			"matchingMode": 6,
			"matchingTeamMode": 4,
			"characterNum": 27,
			"skinCode": 1027002,
			"characterLevel": 19,
			"gameRank": 2,
			"playerKill": 3,
			"playerAssistant": 10,
			"monsterKill": 38,
			"bestWeapon": 2,
			"bestWeaponLevel": 16,
			"masteryLevel": {
				"2": 16,
				"16": 16,
				"6": 16,
				"9": 16,
				"201": 19,
				"202": 6,
				"101": 6,
				"102": 6,
				"103": 6
			},
			"equipment": {
				"0": 116501,
				"1": 202504,
				"2": 201501,
				"3": 203509,
				"4": 204402
			},
			"versionMajor": 3,
			"versionMinor": 0,
			"language": "Korean",
			"skillLevelInfo": {
				"1027200": 5,
				"1027300": 3,
				"1027400": 2,
				"1027500": 3,
				"1027100": 2,
				"3002000": 2,
				"1027700": 2,
				"1027800": 2
			},
			"skillOrderInfo": {
				"1": 1027200,
				"2": 1027300,
				"3": 1027400,
				"4": 1027500,
				"5": 1027100,
				"6": 1027100,
				"7": 1027200,
				"8": 1027200,
				"9": 1027200,
				"10": 1027200,
				"11": 1027500,
				"12": 1027300,
				"13": 1027300,
				"14": 3002000,
				"15": 1027700,
				"16": 1027700,
				"17": 1027500,
				"18": 1027400,
				"19": 3002000,
				"20": 1027800,
				"21": 1027800
			},
			"serverName": "Seoul",
			"maxHp": 2420,
			"maxSp": 1489,
			"attackPower": 356,
			"defense": 113,
			"hpRegen": 1.6,
			"spRegen": 4.73,
			"attackSpeed": 1.82,
			"moveSpeed": 4.11,
			"outOfCombatMoveSpeed": 4.11,
			"sightRange": 10.0,
			"attackRange": 5.33,
			"criticalStrikeChance": 15.0,
			"criticalStrikeDamage": 0.0,
			"coolDownReduction": 0.0,
			"lifeSteal": 0.14,
			"normalLifeSteal": 0.0,
			"skillLifeSteal": 0.0,
			"amplifierToMonster": 12.0,
			"trapDamage": 0.0,
			"bonusCoin": 0,
			"gainExp": 79,
			"baseExp": 79,
			"bonusExp": 0,
			"startDtm": "2023-09-08T23:07:33.033+0900",
			"duration": 746,
			"playTime": 741,
			"watchTime": 0,
			"totalTime": 741,
			"survivableTime": 25,
			"botAdded": 0,
			"botRemain": 0,
			"restrictedAreaAccelerated": 0,
			"safeAreas": 0,
			"teamNumber": 2,
			"preMade": 1,
			"eventMissionResult": {},
			"gainedNormalMmrKFactor": 20.0,
			"victory": 0,
			"craftUncommon": 0,
			"craftRare": 0,
			"craftEpic": 0,
			"craftLegend": 0,
			"damageToPlayer": 20413,
			"damageToPlayer_trap": 0,
			"damageToPlayer_basic": 8360,
			"damageToPlayer_skill": 8838,
			"damageToPlayer_itemSkill": 1237,
			"damageToPlayer_direct": 1978,
			"damageToPlayer_uniqueSkill": 0,
			"damageFromPlayer": 25171,
			"damageFromPlayer_trap": 0,
			"damageFromPlayer_basic": 1748,
			"damageFromPlayer_skill": 21159,
			"damageFromPlayer_itemSkill": 838,
			"damageFromPlayer_direct": 1426,
			"damageFromPlayer_uniqueSkill": 0,
			"damageToMonster": 13031,
			"damageToMonster_trap": 0,
			"damageToMonster_basic": 10107,
			"damageToMonster_skill": 2734,
			"damageToMonster_itemSkill": 190,
			"damageToMonster_direct": 0,
			"damageToMonster_uniqueSkill": 0,
			"damageFromMonster": 473,
			"killMonsters": {
				"11": 36,
				"4": 2
			},
			"healAmount": 13945,
			"teamRecover": 0,
			"protectAbsorb": 3615,
			"addSurveillanceCamera": 0,
			"addTelephotoCamera": 2,
			"removeSurveillanceCamera": 0,
			"removeTelephotoCamera": 0,
			"useHyperLoop": 11,
			"useSecurityConsole": 0,
			"giveUp": 0,
			"teamSpectator": 0,
			"routeIdOfStart": 0,
			"routeSlotId": 0,
			"placeOfStart": "160",
			"matchSize": 8,
			"teamKill": 21,
			"totalFieldKill": 21,
			"accountLevel": 157,
			"killerUserNum": 1092125,
			"killer": "player",
			"killDetail": "혁진이등장",
			"causeOfDeath": "엘레나 패시브",
			"placeOfDeath": "2010",
			"killerCharacter": "Elena",
			"killerWeapon": "Rapier",
			"killerUserNum2": 1736707,
			"killer2": "player",
			"killDetail2": "샌토바보아니다",
			"causeOfDeath2": "나랑 놀자",
			"placeOfDeath2": "2010",
			"killerCharacter2": "Sissela",
			"killerWeapon2": "DirectFire",
			"killerUserNum3": 1092125,
			"killer3": "player",
			"killDetail3": "혁진이등장",
			"causeOfDeath3": "엘레나 Q ",
			"placeOfDeath3": "2030",
			"killerCharacter3": "Elena",
			"killerWeapon3": "Rapier",
			"fishingCount": 0,
			"useEmoticonCount": 10,
			"expireDtm": "2023-12-07T23:20:00.000+0900",
			"traitFirstCore": 7000401,
			"traitFirstSub": [],
			"traitSecondSub": [
				7900801,
				7900301,
				7900101
			],
			"airSupplyOpenCount": [
				0,
				0,
				0,
				0,
				0,
				0,
				0
			],
			"foodCraftCount": [
				0,
				0,
				0,
				0,
				0,
				0,
				0
			],
			"beverageCraftCount": [
				0,
				0,
				0,
				0,
				0,
				0,
				0
			],
			"rankPoint": 0,
			"totalTurbineTakeOver": 4,
			"startingItems": [
				111406,
				202422,
				201304,
				203409,
				204402,
				113409
			],
			"usedNormalHealPack": 6,
			"usedReinforcedHealPack": 0,
			"usedNormalShieldPack": 5,
			"usedReinforceShieldPack": 0,
			"totalVFCredits": [
				46,
				64,
				45,
				46,
				34,
				26,
				90,
				53,
				48,
				25,
				75,
				55,
				6,
				0,
				0,
				0,
				0,
				0,
				0,
				0
			],
			"usedVFCredits": [
				30,
				0,
				80,
				0,
				100,
				0,
				129,
				0,
				0,
				103,
				90,
				38,
				0,
				0,
				0,
				0,
				0,
				0,
				0,
				0
			],
			"sumTotalVFCredits": 613,
			"sumUsedVFCredits": 570,
			"finalInfusion": [
				22,
				7,
				1
			],
			"craftMythic": 0,
			"playerDeaths": 5,
			"killGamma": false,
			"scoredPoint": [
				0,
				0,
				2,
				0,
				0,
				1,
				0,
				1,
				1,
				1,
				0,
				0,
				0,
				0,
				0,
				0,
				0,
				0,
				0,
				0
			],
			"killDetails": "{\"50\":2,\"58\":1}",
			"deathDetails": "{\"50\":2,\"15\":1,\"47\":2}",
			"killsPhaseOne": 0,
			"killsPhaseTwo": 0,
			"killsPhaseThree": 3,
			"deathsPhaseOne": 1,
			"deathsPhaseTwo": 2,
			"deathsPhaseThree": 2,
			"usedPairLoop": 11,
			"ccTimeToPlayer": 29.333334,
			"creditSource": {
				"PhaseStart": 25.0,
				"StartItem": 15.0,
				"InfusionStore": 398.0,
				"ItemShredder": 116.0,
				"KillDrone": 108.0,
				"KillMutantWildDog": 12.0,
				"KillMutantBoar": 16.0,
				"TimeElapsed": 182.0,
				"KillMutantWolf": 16.0,
				"KillPlayerMerge": 47.0,
				"KillAssist": 40.0,
				"KillMutantBear": 36.0,
				"Infusion": 60.0,
				"InfusionRelic": 100.0,
				"InfusionReroll": 12.0
			},
			"boughtInfusion": "{\"10001\":13,\"22\":1,\"2000\":1,\"7\":1,\"1\":1,\"1001\":1}",
			"itemTransferredConsole": [],
			"itemTransferredDrone": [],
			"afk": false,
			"escapeState": 0,
			"totalDoubleKill": 0,
			"totalTripleKill": 0,
			"totalQuadraKill": 0,
			"totalExtraKill": 0,
			"collectItemForLog": [
				0,
				0,
				0,
				0,
				0,
				0,
				0
			],
			"equipFirstItemForLog": {
				"0": [
					111406
				],
				"1": [
					202422
				],
				"2": [
					201304
				],
				"3": [
					203409
				],
				"4": [
					204402
				]
			},
			"battleZone1AreaCode": 0,
			"battleZone1BattleMark": 0,
			"battleZone1ItemCode": [],
			"battleZone2AreaCode": 0,
			"battleZone2BattleMark": 0,
			"battleZone2ItemCode": [],
			"battleZone3AreaCode": 0,
			"battleZone3BattleMark": 0,
			"battleZone3ItemCode": [],
			"battleZonePlayerKill": 0,
			"battleZoneDeaths": 0,
			"battleZone1Winner": 0,
			"battleZone2Winner": 0,
			"battleZone3Winner": 0,
			"battleZone1BattleMarkCount": 0,
			"battleZone2BattleMarkCount": 0,
			"battleZone3BattleMarkCount": 0,
			"tacticalSkillGroup": 500020,
			"tacticalSkillLevel": 1,
			"totalGainVFCredit": 613,
			"killPlayerGainVFCredit": 47,
			"killChickenGainVFCredit": 0,
			"killBoarGainVFCredit": 16,
			"killWildDogGainVFCredit": 12,
			"killWolfGainVFCredit": 16,
			"killBearGainVFCredit": 36,
			"killOmegaGainVFCredit": 0,
			"killBatGainVFCredit": 0,
			"killWicklineGainVFCredit": 0,
			"killAlphaGainVFCredit": 0,
			"killItemBountyGainVFCredit": 0,
			"killDroneGainVFCredit": 108,
			"killGammaGainVFCredit": 0,
			"killTurretGainVFCredit": 0,
			"itemShredderGainVFCredit": 116,
			"totalUseVFCredit": 570,
			"remoteDroneUseVFCreditMySelf": 0,
			"remoteDroneUseVFCreditAlly": 0,
			"transferConsoleFromMaterialUseVFCredit": 0,
			"transferConsoleFromEscapeKeyUseVFCredit": 0,
			"transferConsoleFromRevivalUseVFCredit": 0,
			"tacticalSkillUpgradeUseVFCredit": 0,
			"infusionReRollUseVFCredit": 12,
			"infusionTraitUseVFCredit": 60,
			"infusionRelicUseVFCredit": 100,
			"infusionStoreUseVFCredit": 398,
			"teamElimination": 0,
			"teamDown": 21,
			"teamBattleZoneDown": 0,
			"teamRepeatDown": 0,
			"adaptiveForce": 50,
			"adaptiveForceAttack": 53,
			"adaptiveForceAmplify": 100,
			"skillAmp": 0,
			"campFireCraftUncommon": 0,
			"campFireCraftRare": 0,
			"campFireCraftEpic": 0,
			"campFireCraftLegendary": 0,
			"cobaltRandomPickRemoveCharacter": 0,
			"tacticalSkillUseCount": 9,
			"creditRevivalCount": 0,
			"creditRevivedOthersCount": 0,
			"timeSpentInBriefingRoom": 0,
			"IsLeavingBeforeCreditRevivalTerminate": false,
			"crGetAnimal": 108,
			"crGetMutant": 80,
			"crGetPhaseStart": 25,
			"crGetKill": 47,
			"crGetAssist": 40,
			"crGetTimeElapsed": 182,
			"crGetCreditBonus": 0,
			"crUseRemoteDrone": 0,
			"crUseUpgradeTacticalSkill": 0,
			"crUseTreeOfLife": 0,
			"crUseMeteorite": 0,
			"crUseMythril": 0,
			"crUseForceCore": 0,
			"crUseVFBloodSample": 0,
			"crUseActivationModule": 0,
			"crUseRootkit": 0,
			"mmrGainInGame": 0,
			"isLeavingBeforeCreditRevivalTerminate": false
		}
	]
}